<?xml version="1.0"?>
<!DOCTYPE hibernate-mapping PUBLIC
        "-//Hibernate/Hibernate Mapping DTD 3.0//EN"
        "http://hibernate.sourceforge.net/hibernate-mapping-3.0.dtd">

<hibernate-mapping>
    <class name="Book" table="Books">

        <id name="isbn" column="isbn"  >
            <generator class="assigned" />
        </id>

        <property name="proName" column="title" />
        <property name="proName" column="author1" />
        <property name="proName" column="author2" />
        <property name="proName" column="price" />

    </class>
</hibernate-mapping>